{
	"song": {
		"player1": "scared bf",
		"events": [
			[
				124363.636363636,
				[
					[
						"Play Animation",
						"trans",
						"0"
					]
				]
			],
			[
				127636.363636364,
				[
					[
						"Change Character",
						"1",
						"sfGODNEW"
					]
				]
			]
		],
		"gfVersion": "gf",
		"notes": [
			{
				"sectionNotes": [
					[
						0,
						0,
						1500
					]
				],
				"lengthInSteps": 16,
				"mustHitSection": false
			},
			{
				"sectionNotes": [
					[
						1600,
						3,
						1500
					]
				],
				"lengthInSteps": 16,
				"mustHitSection": false
			},
			{
				"sectionNotes": [
					[
						3200,
						2,
						1500
					]
				],
				"lengthInSteps": 16,
				"mustHitSection": false
			},
			{
				"sectionNotes": [
					[
						4800,
						1,
						700
					],
					[
						5600,
						0,
						700
					]
				],
				"lengthInSteps": 16,
				"mustHitSection": false
			},
			{
				"sectionNotes": [
					[
						6400,
						7,
						700
					],
					[
						6400,
						0,
						1500
					]
				],
				"lengthInSteps": 16,
				"mustHitSection": true
			},
			{
				"sectionNotes": [
					[
						8000,
						3,
						1500
					]
				],
				"lengthInSteps": 16,
				"mustHitSection": true
			},
			{
				"sectionNotes": [
					[
						9600,
						2,
						1500
					]
				],
				"lengthInSteps": 16,
				"mustHitSection": true
			},
			{
				"sectionNotes": [
					[
						11200,
						1,
						700
					],
					[
						12000,
						0,
						700
					]
				],
				"lengthInSteps": 16,
				"mustHitSection": true
			},
			{
				"sectionNotes": [
					[
						12800,
						1,
						1500
					]
				],
				"lengthInSteps": 16,
				"mustHitSection": false
			},
			{
				"sectionNotes": [
					[
						14400,
						0,
						1500
					]
				],
				"lengthInSteps": 16,
				"mustHitSection": false
			},
			{
				"sectionNotes": [
					[
						16000,
						3,
						1500
					]
				],
				"lengthInSteps": 16,
				"mustHitSection": false
			},
			{
				"sectionNotes": [
					[
						17600,
						1,
						1500
					]
				],
				"lengthInSteps": 16,
				"mustHitSection": false
			},
			{
				"sectionNotes": [
					[
						19200,
						1,
						1500
					]
				],
				"lengthInSteps": 16,
				"mustHitSection": true
			},
			{
				"sectionNotes": [
					[
						20800,
						0,
						1500
					]
				],
				"lengthInSteps": 16,
				"mustHitSection": true
			},
			{
				"sectionNotes": [
					[
						22400,
						3,
						1500
					]
				],
				"lengthInSteps": 16,
				"mustHitSection": true
			},
			{
				"sectionNotes": [
					[
						24000,
						1,
						1500
					],
					[
						24800,
						3,
						700
					],
					[
						25200,
						0,
						300
					]
				],
				"lengthInSteps": 16,
				"mustHitSection": true
			},
			{
				"sectionNotes": [],
				"lengthInSteps": 16,
				"mustHitSection": true
			},
			{
				"sectionNotes": [],
				"lengthInSteps": 16,
				"mustHitSection": false
			},
			{
				"sectionNotes": [],
				"lengthInSteps": 16,
				"mustHitSection": true
			},
			{
				"sectionNotes": [],
				"lengthInSteps": 16,
				"mustHitSection": false
			},
			{
				"sectionNotes": [
					[
						32000,
						0,
						0
					],
					[
						32100,
						3,
						0
					],
					[
						32200,
						2,
						0
					],
					[
						32300,
						0,
						0
					],
					[
						32400,
						2,
						0
					],
					[
						32500,
						1,
						0
					],
					[
						32600,
						2,
						0
					],
					[
						32700,
						0,
						0
					],
					[
						33200,
						2,
						300
					],
					[
						32800,
						3,
						300
					],
					[
						33000,
						0,
						300
					]
				],
				"lengthInSteps": 16,
				"mustHitSection": false
			},
			{
				"sectionNotes": [
					[
						33600,
						1,
						300
					],
					[
						34000,
						0,
						300
					],
					[
						33800,
						3,
						300
					],
					[
						34400,
						1,
						300
					],
					[
						34600,
						0,
						100
					],
					[
						34800,
						2,
						300
					],
					[
						35000,
						1,
						100
					]
				],
				"lengthInSteps": 16,
				"mustHitSection": false
			},
			{
				"sectionNotes": [
					[
						35200,
						3,
						300
					],
					[
						35400,
						0,
						100
					],
					[
						35600,
						1,
						100
					],
					[
						35800,
						0,
						0
					],
					[
						35900,
						2,
						0
					],
					[
						36000,
						1,
						100
					],
					[
						36200,
						0,
						0
					],
					[
						36300,
						2,
						0
					],
					[
						36400,
						1,
						0
					],
					[
						36600,
						2,
						0
					],
					[
						36700,
						0,
						0
					],
					[
						36400,
						3,
						0
					]
				],
				"lengthInSteps": 16,
				"mustHitSection": false
			},
			{
				"sectionNotes": [
					[
						36800,
						1,
						0
					],
					[
						36900,
						3,
						0
					],
					[
						37000,
						0,
						0
					],
					[
						37100,
						3,
						100
					],
					[
						37200,
						2,
						0
					],
					[
						37300,
						0,
						0
					],
					[
						37400,
						3,
						0
					],
					[
						37500,
						1,
						0
					],
					[
						37800,
						3,
						100
					],
					[
						38200,
						0,
						100
					],
					[
						37600,
						0,
						100
					],
					[
						38000,
						1,
						300
					]
				],
				"lengthInSteps": 16,
				"mustHitSection": false
			},
			{
				"sectionNotes": [
					[
						38400,
						0,
						0
					],
					[
						38500,
						3,
						0
					],
					[
						38600,
						2,
						0
					],
					[
						38700,
						0,
						0
					],
					[
						38800,
						2,
						0
					],
					[
						38900,
						1,
						0
					],
					[
						39000,
						2,
						0
					],
					[
						39100,
						0,
						0
					],
					[
						39600,
						2,
						300
					],
					[
						39200,
						3,
						300
					],
					[
						39400,
						0,
						300
					],
					[
						38400,
						7,
						100
					],
					[
						38800,
						7,
						100
					],
					[
						39000,
						7,
						100
					],
					[
						39400,
						7,
						100
					],
					[
						39600,
						6,
						100
					],
					[
						39800,
						5,
						100
					]
				],
				"lengthInSteps": 16,
				"mustHitSection": true
			},
			{
				"sectionNotes": [
					[
						40000,
						1,
						300
					],
					[
						40400,
						0,
						300
					],
					[
						40200,
						3,
						300
					],
					[
						40800,
						1,
						300
					],
					[
						41000,
						0,
						100
					],
					[
						41200,
						2,
						300
					],
					[
						41400,
						1,
						100
					],
					[
						40000,
						4,
						100
					],
					[
						40400,
						4,
						100
					],
					[
						41000,
						5,
						100
					],
					[
						41200,
						7,
						100
					],
					[
						41400,
						6,
						100
					],
					[
						40600,
						4,
						100
					],
					[
						40700,
						7,
						0
					]
				],
				"lengthInSteps": 16,
				"mustHitSection": true
			},
			{
				"sectionNotes": [
					[
						41600,
						3,
						300
					],
					[
						41800,
						0,
						100
					],
					[
						42000,
						1,
						100
					],
					[
						42200,
						0,
						0
					],
					[
						42300,
						2,
						0
					],
					[
						42400,
						1,
						100
					],
					[
						42600,
						0,
						0
					],
					[
						42700,
						2,
						0
					],
					[
						42800,
						1,
						0
					],
					[
						43000,
						2,
						0
					],
					[
						43100,
						0,
						0
					],
					[
						42800,
						3,
						0
					],
					[
						41600,
						4,
						100
					]
				],
				"lengthInSteps": 16,
				"mustHitSection": true
			},
			{
				"sectionNotes": [
					[
						43200,
						1,
						0
					],
					[
						43300,
						3,
						0
					],
					[
						43400,
						0,
						0
					],
					[
						43500,
						3,
						100
					],
					[
						43600,
						2,
						0
					],
					[
						43700,
						0,
						0
					],
					[
						43800,
						3,
						0
					],
					[
						43900,
						1,
						0
					],
					[
						44200,
						3,
						100
					],
					[
						44600,
						0,
						100
					],
					[
						44000,
						0,
						100
					],
					[
						44400,
						1,
						300
					]
				],
				"lengthInSteps": 16,
				"mustHitSection": true
			},
			{
				"sectionNotes": [
					[
						44800,
						0,
						0
					],
					[
						44900,
						3,
						0
					],
					[
						45000,
						2,
						0
					],
					[
						45100,
						0,
						0
					],
					[
						45200,
						2,
						0
					],
					[
						45300,
						1,
						0
					],
					[
						45400,
						2,
						0
					],
					[
						45500,
						0,
						0
					],
					[
						46000,
						2,
						300
					],
					[
						45600,
						3,
						300
					],
					[
						45800,
						0,
						300
					]
				],
				"lengthInSteps": 16,
				"mustHitSection": false
			},
			{
				"sectionNotes": [
					[
						46400,
						0,
						0
					]
				],
				"lengthInSteps": 16,
				"mustHitSection": false
			},
			{
				"sectionNotes": [],
				"lengthInSteps": 16,
				"mustHitSection": true
			},
			{
				"sectionNotes": [],
				"lengthInSteps": 16,
				"mustHitSection": true
			},
			{
				"sectionNotes": [],
				"lengthInSteps": 16,
				"mustHitSection": false
			},
			{
				"sectionNotes": [],
				"lengthInSteps": 16,
				"mustHitSection": false
			},
			{
				"sectionNotes": [],
				"lengthInSteps": 16,
				"mustHitSection": false
			},
			{
				"sectionNotes": [],
				"lengthInSteps": 16,
				"mustHitSection": false
			},
			{
				"sectionNotes": [],
				"lengthInSteps": 16,
				"mustHitSection": false
			},
			{
				"sectionNotes": [],
				"lengthInSteps": 16,
				"mustHitSection": false
			},
			{
				"sectionNotes": [],
				"lengthInSteps": 16,
				"mustHitSection": false
			},
			{
				"sectionNotes": [],
				"lengthInSteps": 16,
				"mustHitSection": false
			},
			{
				"sectionNotes": [],
				"lengthInSteps": 16,
				"mustHitSection": true
			},
			{
				"sectionNotes": [],
				"lengthInSteps": 16,
				"mustHitSection": true
			},
			{
				"sectionNotes": [],
				"lengthInSteps": 16,
				"mustHitSection": true
			},
			{
				"sectionNotes": [],
				"lengthInSteps": 16,
				"mustHitSection": true
			},
			{
				"sectionNotes": [],
				"lengthInSteps": 16,
				"mustHitSection": true
			},
			{
				"sectionNotes": [],
				"lengthInSteps": 16,
				"mustHitSection": false
			},
			{
				"sectionNotes": [],
				"lengthInSteps": 16,
				"mustHitSection": false
			},
			{
				"sectionNotes": [],
				"lengthInSteps": 16,
				"mustHitSection": false
			},
			{
				"sectionNotes": [],
				"lengthInSteps": 16,
				"mustHitSection": false
			},
			{
				"sectionNotes": [],
				"lengthInSteps": 16,
				"mustHitSection": false
			},
			{
				"sectionNotes": [],
				"lengthInSteps": 16,
				"mustHitSection": true
			},
			{
				"sectionNotes": [],
				"lengthInSteps": 16,
				"mustHitSection": true
			},
			{
				"sectionNotes": [],
				"lengthInSteps": 16,
				"mustHitSection": false
			},
			{
				"sectionNotes": [],
				"lengthInSteps": 16,
				"mustHitSection": false
			},
			{
				"sectionNotes": [],
				"lengthInSteps": 16,
				"mustHitSection": true
			},
			{
				"sectionNotes": [],
				"lengthInSteps": 16,
				"mustHitSection": true
			},
			{
				"sectionNotes": [],
				"lengthInSteps": 16,
				"mustHitSection": true
			},
			{
				"sectionNotes": [],
				"lengthInSteps": 16,
				"mustHitSection": true
			},
			{
				"sectionNotes": [],
				"lengthInSteps": 16,
				"mustHitSection": false
			},
			{
				"sectionNotes": [],
				"lengthInSteps": 16,
				"mustHitSection": false
			},
			{
				"sectionNotes": [],
				"lengthInSteps": 16,
				"mustHitSection": false
			},
			{
				"sectionNotes": [],
				"lengthInSteps": 16,
				"mustHitSection": false
			},
			{
				"sectionNotes": [],
				"lengthInSteps": 16,
				"mustHitSection": false
			},
			{
				"sectionNotes": [],
				"lengthInSteps": 16,
				"mustHitSection": false
			},
			{
				"sectionNotes": [],
				"lengthInSteps": 16,
				"mustHitSection": true
			},
			{
				"sectionNotes": [],
				"lengthInSteps": 16,
				"mustHitSection": true
			},
			{
				"sectionNotes": [],
				"lengthInSteps": 16,
				"mustHitSection": true
			},
			{
				"sectionNotes": [],
				"lengthInSteps": 16,
				"mustHitSection": true
			},
			{
				"sectionNotes": [],
				"lengthInSteps": 16,
				"mustHitSection": false
			},
			{
				"sectionNotes": [],
				"lengthInSteps": 16,
				"mustHitSection": false
			},
			{
				"sectionNotes": [],
				"lengthInSteps": 16,
				"mustHitSection": true
			},
			{
				"sectionNotes": [],
				"lengthInSteps": 16,
				"mustHitSection": true
			},
			{
				"sectionNotes": [],
				"lengthInSteps": 16,
				"mustHitSection": true
			},
			{
				"sectionNotes": [],
				"lengthInSteps": 16,
				"mustHitSection": true
			},
			{
				"sectionNotes": [],
				"lengthInSteps": 16,
				"mustHitSection": false
			},
			{
				"sectionNotes": [],
				"lengthInSteps": 16,
				"mustHitSection": false
			},
			{
				"sectionNotes": [],
				"lengthInSteps": 16,
				"mustHitSection": false
			},
			{
				"sectionNotes": [],
				"lengthInSteps": 16,
				"mustHitSection": false
			},
			{
				"sectionNotes": [],
				"lengthInSteps": 16,
				"mustHitSection": true
			},
			{
				"sectionNotes": [],
				"lengthInSteps": 16,
				"mustHitSection": true
			},
			{
				"sectionNotes": [],
				"lengthInSteps": 16,
				"mustHitSection": true
			},
			{
				"sectionNotes": [],
				"lengthInSteps": 16,
				"mustHitSection": true
			},
			{
				"sectionNotes": [],
				"lengthInSteps": 16,
				"mustHitSection": false
			},
			{
				"sectionNotes": [],
				"lengthInSteps": 16,
				"mustHitSection": false
			},
			{
				"sectionNotes": [],
				"lengthInSteps": 16,
				"mustHitSection": false
			},
			{
				"sectionNotes": [],
				"lengthInSteps": 16,
				"mustHitSection": false
			},
			{
				"sectionNotes": [],
				"lengthInSteps": 16,
				"mustHitSection": true
			},
			{
				"sectionNotes": [],
				"lengthInSteps": 16,
				"mustHitSection": true
			},
			{
				"sectionNotes": [],
				"lengthInSteps": 16,
				"mustHitSection": true
			},
			{
				"sectionNotes": [],
				"lengthInSteps": 16,
				"mustHitSection": true
			},
			{
				"sectionNotes": [],
				"lengthInSteps": 16,
				"mustHitSection": true
			},
			{
				"sectionNotes": [],
				"lengthInSteps": 16,
				"mustHitSection": true
			},
			{
				"sectionNotes": [],
				"lengthInSteps": 16,
				"mustHitSection": true
			},
			{
				"sectionNotes": [],
				"lengthInSteps": 16,
				"mustHitSection": true
			},
			{
				"lengthInSteps": 16,
				"typeOfSection": 0,
				"sectionNotes": [],
				"altAnim": false,
				"bpm": 180,
				"changeBPM": false,
				"mustHitSection": true
			},
			{
				"lengthInSteps": 16,
				"typeOfSection": 0,
				"sectionNotes": [],
				"altAnim": false,
				"bpm": 180,
				"changeBPM": false,
				"mustHitSection": true
			},
			{
				"lengthInSteps": 16,
				"typeOfSection": 0,
				"sectionNotes": [],
				"altAnim": false,
				"bpm": 180,
				"changeBPM": false,
				"mustHitSection": true
			},
			{
				"lengthInSteps": 16,
				"typeOfSection": 0,
				"sectionNotes": [],
				"altAnim": false,
				"bpm": 180,
				"changeBPM": false,
				"mustHitSection": true
			},
			{
				"lengthInSteps": 16,
				"typeOfSection": 0,
				"sectionNotes": [],
				"altAnim": false,
				"bpm": 180,
				"changeBPM": false,
				"mustHitSection": true
			},
			{
				"lengthInSteps": 16,
				"typeOfSection": 0,
				"sectionNotes": [],
				"altAnim": false,
				"bpm": 180,
				"changeBPM": false,
				"mustHitSection": true
			},
			{
				"lengthInSteps": 16,
				"typeOfSection": 0,
				"sectionNotes": [],
				"altAnim": false,
				"bpm": 180,
				"changeBPM": false,
				"mustHitSection": true
			},
			{
				"lengthInSteps": 16,
				"typeOfSection": 0,
				"sectionNotes": [],
				"altAnim": false,
				"bpm": 180,
				"changeBPM": false,
				"mustHitSection": true
			},
			{
				"lengthInSteps": 16,
				"typeOfSection": 0,
				"sectionNotes": [],
				"altAnim": false,
				"bpm": 180,
				"changeBPM": false,
				"mustHitSection": true
			},
			{
				"lengthInSteps": 16,
				"typeOfSection": 0,
				"sectionNotes": [],
				"altAnim": false,
				"bpm": 180,
				"changeBPM": false,
				"mustHitSection": true
			},
			{
				"lengthInSteps": 16,
				"typeOfSection": 0,
				"sectionNotes": [],
				"altAnim": false,
				"bpm": 180,
				"changeBPM": false,
				"mustHitSection": true
			},
			{
				"lengthInSteps": 16,
				"typeOfSection": 0,
				"sectionNotes": [],
				"altAnim": false,
				"bpm": 180,
				"changeBPM": false,
				"mustHitSection": true
			},
			{
				"lengthInSteps": 16,
				"typeOfSection": 0,
				"sectionNotes": [],
				"altAnim": false,
				"bpm": 180,
				"changeBPM": false,
				"mustHitSection": true
			},
			{
				"lengthInSteps": 16,
				"typeOfSection": 0,
				"sectionNotes": [],
				"altAnim": false,
				"bpm": 180,
				"changeBPM": false,
				"mustHitSection": true
			},
			{
				"lengthInSteps": 16,
				"typeOfSection": 0,
				"sectionNotes": [],
				"altAnim": false,
				"bpm": 180,
				"changeBPM": false,
				"mustHitSection": true
			},
			{
				"lengthInSteps": 16,
				"typeOfSection": 0,
				"sectionNotes": [],
				"altAnim": false,
				"bpm": 180,
				"changeBPM": false,
				"mustHitSection": true
			},
			{
				"lengthInSteps": 16,
				"typeOfSection": 0,
				"sectionNotes": [],
				"altAnim": false,
				"bpm": 180,
				"changeBPM": false,
				"mustHitSection": true
			},
			{
				"lengthInSteps": 16,
				"typeOfSection": 0,
				"sectionNotes": [],
				"altAnim": false,
				"bpm": 180,
				"changeBPM": false,
				"mustHitSection": true
			},
			{
				"lengthInSteps": 16,
				"typeOfSection": 0,
				"sectionNotes": [],
				"altAnim": false,
				"bpm": 180,
				"changeBPM": false,
				"mustHitSection": true
			},
			{
				"lengthInSteps": 16,
				"typeOfSection": 0,
				"sectionNotes": [],
				"altAnim": false,
				"bpm": 180,
				"changeBPM": false,
				"mustHitSection": true
			},
			{
				"lengthInSteps": 16,
				"typeOfSection": 0,
				"sectionNotes": [],
				"altAnim": false,
				"bpm": 180,
				"changeBPM": false,
				"mustHitSection": true
			},
			{
				"lengthInSteps": 16,
				"typeOfSection": 0,
				"sectionNotes": [],
				"altAnim": false,
				"bpm": 180,
				"changeBPM": false,
				"mustHitSection": true
			},
			{
				"lengthInSteps": 16,
				"typeOfSection": 0,
				"sectionNotes": [],
				"altAnim": false,
				"bpm": 180,
				"changeBPM": false,
				"mustHitSection": true
			},
			{
				"lengthInSteps": 16,
				"typeOfSection": 0,
				"sectionNotes": [],
				"altAnim": false,
				"bpm": 180,
				"changeBPM": false,
				"mustHitSection": true
			},
			{
				"lengthInSteps": 16,
				"typeOfSection": 0,
				"sectionNotes": [],
				"altAnim": false,
				"bpm": 180,
				"changeBPM": false,
				"mustHitSection": true
			},
			{
				"lengthInSteps": 16,
				"typeOfSection": 0,
				"sectionNotes": [],
				"altAnim": false,
				"bpm": 180,
				"changeBPM": false,
				"mustHitSection": true
			},
			{
				"lengthInSteps": 16,
				"typeOfSection": 0,
				"sectionNotes": [],
				"altAnim": false,
				"bpm": 180,
				"changeBPM": false,
				"mustHitSection": true
			},
			{
				"lengthInSteps": 16,
				"typeOfSection": 0,
				"sectionNotes": [],
				"altAnim": false,
				"bpm": 180,
				"changeBPM": false,
				"mustHitSection": true
			},
			{
				"lengthInSteps": 16,
				"typeOfSection": 0,
				"sectionNotes": [],
				"altAnim": false,
				"bpm": 180,
				"changeBPM": false,
				"mustHitSection": true
			},
			{
				"lengthInSteps": 16,
				"typeOfSection": 0,
				"sectionNotes": [],
				"altAnim": false,
				"bpm": 180,
				"changeBPM": false,
				"mustHitSection": true
			},
			{
				"lengthInSteps": 16,
				"typeOfSection": 0,
				"sectionNotes": [],
				"altAnim": false,
				"bpm": 180,
				"changeBPM": false,
				"mustHitSection": true
			},
			{
				"lengthInSteps": 16,
				"typeOfSection": 0,
				"sectionNotes": [],
				"altAnim": false,
				"bpm": 180,
				"changeBPM": false,
				"mustHitSection": true
			},
			{
				"lengthInSteps": 16,
				"typeOfSection": 0,
				"sectionNotes": [],
				"altAnim": false,
				"bpm": 180,
				"changeBPM": false,
				"mustHitSection": true
			},
			{
				"lengthInSteps": 16,
				"typeOfSection": 0,
				"sectionNotes": [],
				"altAnim": false,
				"bpm": 180,
				"changeBPM": false,
				"mustHitSection": true
			},
			{
				"lengthInSteps": 16,
				"typeOfSection": 0,
				"sectionNotes": [],
				"altAnim": false,
				"bpm": 180,
				"changeBPM": false,
				"mustHitSection": true
			},
			{
				"lengthInSteps": 16,
				"typeOfSection": 0,
				"sectionNotes": [],
				"altAnim": false,
				"bpm": 180,
				"changeBPM": false,
				"mustHitSection": true
			},
			{
				"lengthInSteps": 16,
				"typeOfSection": 0,
				"sectionNotes": [],
				"altAnim": false,
				"bpm": 180,
				"changeBPM": false,
				"mustHitSection": true
			},
			{
				"lengthInSteps": 16,
				"typeOfSection": 0,
				"sectionNotes": [],
				"altAnim": false,
				"bpm": 180,
				"changeBPM": false,
				"mustHitSection": true
			},
			{
				"lengthInSteps": 16,
				"typeOfSection": 0,
				"sectionNotes": [],
				"altAnim": false,
				"bpm": 180,
				"changeBPM": false,
				"mustHitSection": true
			},
			{
				"lengthInSteps": 16,
				"typeOfSection": 0,
				"sectionNotes": [],
				"altAnim": false,
				"bpm": 180,
				"changeBPM": false,
				"mustHitSection": true
			},
			{
				"lengthInSteps": 16,
				"typeOfSection": 0,
				"sectionNotes": [],
				"altAnim": false,
				"bpm": 180,
				"changeBPM": false,
				"mustHitSection": true
			},
			{
				"lengthInSteps": 16,
				"typeOfSection": 0,
				"sectionNotes": [],
				"altAnim": false,
				"bpm": 180,
				"changeBPM": false,
				"mustHitSection": true
			},
			{
				"lengthInSteps": 16,
				"typeOfSection": 0,
				"sectionNotes": [],
				"altAnim": false,
				"bpm": 180,
				"changeBPM": false,
				"mustHitSection": true
			},
			{
				"lengthInSteps": 16,
				"typeOfSection": 0,
				"sectionNotes": [],
				"altAnim": false,
				"bpm": 180,
				"changeBPM": false,
				"mustHitSection": true
			},
			{
				"lengthInSteps": 16,
				"typeOfSection": 0,
				"sectionNotes": [],
				"altAnim": false,
				"bpm": 180,
				"changeBPM": false,
				"mustHitSection": true
			},
			{
				"lengthInSteps": 16,
				"typeOfSection": 0,
				"sectionNotes": [],
				"altAnim": false,
				"bpm": 180,
				"changeBPM": false,
				"mustHitSection": true
			},
			{
				"lengthInSteps": 16,
				"typeOfSection": 0,
				"sectionNotes": [],
				"altAnim": false,
				"bpm": 180,
				"changeBPM": false,
				"mustHitSection": true
			},
			{
				"lengthInSteps": 16,
				"typeOfSection": 0,
				"sectionNotes": [],
				"altAnim": false,
				"bpm": 180,
				"changeBPM": false,
				"mustHitSection": true
			},
			{
				"lengthInSteps": 16,
				"typeOfSection": 0,
				"sectionNotes": [],
				"altAnim": false,
				"bpm": 180,
				"changeBPM": false,
				"mustHitSection": true
			},
			{
				"lengthInSteps": 16,
				"typeOfSection": 0,
				"sectionNotes": [],
				"altAnim": false,
				"bpm": 180,
				"changeBPM": false,
				"mustHitSection": true
			},
			{
				"lengthInSteps": 16,
				"typeOfSection": 0,
				"sectionNotes": [],
				"altAnim": false,
				"bpm": 180,
				"changeBPM": false,
				"mustHitSection": true
			},
			{
				"lengthInSteps": 16,
				"typeOfSection": 0,
				"sectionNotes": [],
				"altAnim": false,
				"bpm": 180,
				"changeBPM": false,
				"mustHitSection": true
			},
			{
				"lengthInSteps": 16,
				"typeOfSection": 0,
				"sectionNotes": [],
				"altAnim": false,
				"bpm": 180,
				"changeBPM": false,
				"mustHitSection": true
			},
			{
				"lengthInSteps": 16,
				"typeOfSection": 0,
				"sectionNotes": [],
				"altAnim": false,
				"bpm": 180,
				"changeBPM": false,
				"mustHitSection": true
			},
			{
				"lengthInSteps": 16,
				"typeOfSection": 0,
				"sectionNotes": [],
				"altAnim": false,
				"bpm": 180,
				"changeBPM": false,
				"mustHitSection": true
			},
			{
				"lengthInSteps": 16,
				"typeOfSection": 0,
				"sectionNotes": [],
				"altAnim": false,
				"bpm": 180,
				"changeBPM": false,
				"mustHitSection": true
			},
			{
				"lengthInSteps": 16,
				"typeOfSection": 0,
				"sectionNotes": [],
				"altAnim": false,
				"bpm": 180,
				"changeBPM": false,
				"mustHitSection": true
			},
			{
				"lengthInSteps": 16,
				"typeOfSection": 0,
				"sectionNotes": [],
				"altAnim": false,
				"bpm": 180,
				"changeBPM": false,
				"mustHitSection": true
			},
			{
				"lengthInSteps": 16,
				"typeOfSection": 0,
				"sectionNotes": [],
				"altAnim": false,
				"bpm": 180,
				"changeBPM": false,
				"mustHitSection": true
			},
			{
				"lengthInSteps": 16,
				"typeOfSection": 0,
				"sectionNotes": [],
				"altAnim": false,
				"bpm": 180,
				"changeBPM": false,
				"mustHitSection": true
			},
			{
				"lengthInSteps": 16,
				"typeOfSection": 0,
				"sectionNotes": [],
				"altAnim": false,
				"bpm": 180,
				"changeBPM": false,
				"mustHitSection": true
			},
			{
				"lengthInSteps": 16,
				"typeOfSection": 0,
				"sectionNotes": [],
				"altAnim": false,
				"bpm": 180,
				"changeBPM": false,
				"mustHitSection": true
			},
			{
				"lengthInSteps": 16,
				"typeOfSection": 0,
				"sectionNotes": [],
				"altAnim": false,
				"bpm": 180,
				"changeBPM": false,
				"mustHitSection": true
			},
			{
				"lengthInSteps": 16,
				"typeOfSection": 0,
				"sectionNotes": [],
				"altAnim": false,
				"bpm": 180,
				"changeBPM": false,
				"mustHitSection": true
			},
			{
				"lengthInSteps": 16,
				"typeOfSection": 0,
				"sectionNotes": [],
				"altAnim": false,
				"bpm": 180,
				"changeBPM": false,
				"mustHitSection": true
			},
			{
				"lengthInSteps": 16,
				"typeOfSection": 0,
				"sectionNotes": [],
				"altAnim": false,
				"bpm": 180,
				"changeBPM": false,
				"mustHitSection": true
			},
			{
				"lengthInSteps": 16,
				"typeOfSection": 0,
				"sectionNotes": [],
				"altAnim": false,
				"bpm": 180,
				"changeBPM": false,
				"mustHitSection": true
			},
			{
				"lengthInSteps": 16,
				"typeOfSection": 0,
				"sectionNotes": [],
				"altAnim": false,
				"bpm": 180,
				"changeBPM": false,
				"mustHitSection": true
			},
			{
				"lengthInSteps": 16,
				"typeOfSection": 0,
				"sectionNotes": [],
				"altAnim": false,
				"bpm": 180,
				"changeBPM": false,
				"mustHitSection": true
			},
			{
				"lengthInSteps": 16,
				"typeOfSection": 0,
				"sectionNotes": [],
				"altAnim": false,
				"bpm": 180,
				"changeBPM": false,
				"mustHitSection": true
			},
			{
				"lengthInSteps": 16,
				"typeOfSection": 0,
				"sectionNotes": [],
				"altAnim": false,
				"bpm": 180,
				"changeBPM": false,
				"mustHitSection": true
			},
			{
				"lengthInSteps": 16,
				"typeOfSection": 0,
				"sectionNotes": [],
				"altAnim": false,
				"bpm": 180,
				"changeBPM": false,
				"mustHitSection": true
			},
			{
				"lengthInSteps": 16,
				"typeOfSection": 0,
				"sectionNotes": [],
				"altAnim": false,
				"bpm": 180,
				"changeBPM": false,
				"mustHitSection": true
			},
			{
				"lengthInSteps": 16,
				"typeOfSection": 0,
				"sectionNotes": [],
				"altAnim": false,
				"bpm": 180,
				"changeBPM": false,
				"mustHitSection": true
			},
			{
				"lengthInSteps": 16,
				"typeOfSection": 0,
				"sectionNotes": [],
				"altAnim": false,
				"bpm": 180,
				"changeBPM": false,
				"mustHitSection": true
			},
			{
				"lengthInSteps": 16,
				"typeOfSection": 0,
				"sectionNotes": [],
				"altAnim": false,
				"bpm": 180,
				"changeBPM": false,
				"mustHitSection": true
			},
			{
				"lengthInSteps": 16,
				"typeOfSection": 0,
				"sectionNotes": [],
				"altAnim": false,
				"bpm": 180,
				"changeBPM": false,
				"mustHitSection": true
			},
			{
				"lengthInSteps": 16,
				"typeOfSection": 0,
				"sectionNotes": [],
				"altAnim": false,
				"bpm": 180,
				"changeBPM": false,
				"mustHitSection": true
			},
			{
				"lengthInSteps": 16,
				"typeOfSection": 0,
				"sectionNotes": [],
				"altAnim": false,
				"bpm": 180,
				"changeBPM": false,
				"mustHitSection": true
			},
			{
				"lengthInSteps": 16,
				"typeOfSection": 0,
				"sectionNotes": [],
				"altAnim": false,
				"bpm": 180,
				"changeBPM": false,
				"mustHitSection": true
			},
			{
				"lengthInSteps": 16,
				"typeOfSection": 0,
				"sectionNotes": [],
				"altAnim": false,
				"bpm": 180,
				"changeBPM": false,
				"mustHitSection": true
			},
			{
				"sectionNotes": [],
				"typeOfSection": 0,
				"lengthInSteps": 16,
				"altAnim": false,
				"mustHitSection": true,
				"changeBPM": false,
				"bpm": 180
			},
			{
				"sectionNotes": [],
				"typeOfSection": 0,
				"lengthInSteps": 16,
				"altAnim": false,
				"mustHitSection": true,
				"changeBPM": false,
				"bpm": 180
			},
			{
				"sectionNotes": [],
				"typeOfSection": 0,
				"lengthInSteps": 16,
				"altAnim": false,
				"mustHitSection": true,
				"changeBPM": false,
				"bpm": 185
			},
			{
				"lengthInSteps": 16,
				"typeOfSection": 0,
				"sectionNotes": [],
				"altAnim": false,
				"bpm": 185,
				"changeBPM": false,
				"mustHitSection": true
			},
			{
				"lengthInSteps": 16,
				"typeOfSection": 0,
				"sectionNotes": [],
				"altAnim": false,
				"bpm": 185,
				"changeBPM": false,
				"mustHitSection": true
			},
			{
				"lengthInSteps": 16,
				"typeOfSection": 0,
				"sectionNotes": [],
				"altAnim": false,
				"bpm": 185,
				"changeBPM": false,
				"mustHitSection": true
			},
			{
				"lengthInSteps": 16,
				"typeOfSection": 0,
				"sectionNotes": [],
				"altAnim": false,
				"bpm": 185,
				"changeBPM": false,
				"mustHitSection": true
			},
			{
				"lengthInSteps": 16,
				"typeOfSection": 0,
				"sectionNotes": [],
				"altAnim": false,
				"bpm": 185,
				"changeBPM": false,
				"mustHitSection": true
			},
			{
				"lengthInSteps": 16,
				"typeOfSection": 0,
				"sectionNotes": [],
				"altAnim": false,
				"bpm": 185,
				"changeBPM": false,
				"mustHitSection": true
			},
			{
				"lengthInSteps": 16,
				"typeOfSection": 0,
				"sectionNotes": [],
				"altAnim": false,
				"bpm": 185,
				"changeBPM": false,
				"mustHitSection": true
			},
			{
				"lengthInSteps": 16,
				"typeOfSection": 0,
				"sectionNotes": [],
				"altAnim": false,
				"bpm": 185,
				"changeBPM": false,
				"mustHitSection": true
			},
			{
				"lengthInSteps": 16,
				"typeOfSection": 0,
				"sectionNotes": [],
				"altAnim": false,
				"bpm": 185,
				"changeBPM": false,
				"mustHitSection": true
			},
			{
				"sectionNotes": [],
				"typeOfSection": 0,
				"lengthInSteps": 16,
				"altAnim": false,
				"mustHitSection": true,
				"changeBPM": false,
				"bpm": 185
			},
			{
				"lengthInSteps": 16,
				"typeOfSection": 0,
				"sectionNotes": [],
				"altAnim": false,
				"bpm": 185,
				"changeBPM": false,
				"mustHitSection": true
			},
			{
				"sectionNotes": [],
				"typeOfSection": 0,
				"lengthInSteps": 16,
				"altAnim": false,
				"mustHitSection": true,
				"changeBPM": false,
				"bpm": 185
			},
			{
				"sectionNotes": [],
				"typeOfSection": 0,
				"lengthInSteps": 16,
				"altAnim": false,
				"mustHitSection": true,
				"changeBPM": false,
				"bpm": 185
			},
			{
				"sectionNotes": [],
				"typeOfSection": 0,
				"lengthInSteps": 16,
				"altAnim": false,
				"mustHitSection": true,
				"changeBPM": false,
				"bpm": 185
			},
			{
				"sectionNotes": [],
				"typeOfSection": 0,
				"lengthInSteps": 16,
				"altAnim": false,
				"mustHitSection": true,
				"changeBPM": false,
				"bpm": 185
			},
			{
				"lengthInSteps": 16,
				"typeOfSection": 0,
				"sectionNotes": [],
				"altAnim": false,
				"bpm": 185,
				"changeBPM": false,
				"mustHitSection": true
			},
			{
				"sectionNotes": [],
				"typeOfSection": 0,
				"lengthInSteps": 16,
				"altAnim": false,
				"mustHitSection": true,
				"changeBPM": false,
				"bpm": 185
			},
			{
				"sectionNotes": [],
				"typeOfSection": 0,
				"lengthInSteps": 16,
				"altAnim": false,
				"mustHitSection": true,
				"changeBPM": false,
				"bpm": 185
			},
			{
				"sectionNotes": [],
				"typeOfSection": 0,
				"lengthInSteps": 16,
				"altAnim": false,
				"mustHitSection": true,
				"changeBPM": false,
				"bpm": 185
			},
			{
				"sectionNotes": [],
				"typeOfSection": 0,
				"lengthInSteps": 16,
				"altAnim": false,
				"mustHitSection": true,
				"changeBPM": false,
				"bpm": 185
			},
			{
				"sectionNotes": [],
				"typeOfSection": 0,
				"lengthInSteps": 16,
				"altAnim": false,
				"mustHitSection": true,
				"changeBPM": false,
				"bpm": 185
			},
			{
				"lengthInSteps": 16,
				"typeOfSection": 0,
				"sectionNotes": [],
				"altAnim": false,
				"bpm": 185,
				"changeBPM": false,
				"mustHitSection": true
			},
			{
				"lengthInSteps": 16,
				"typeOfSection": 0,
				"sectionNotes": [],
				"altAnim": false,
				"bpm": 185,
				"changeBPM": false,
				"mustHitSection": true
			},
			{
				"lengthInSteps": 16,
				"typeOfSection": 0,
				"sectionNotes": [],
				"altAnim": false,
				"bpm": 185,
				"changeBPM": false,
				"mustHitSection": true
			},
			{
				"sectionNotes": [],
				"typeOfSection": 0,
				"lengthInSteps": 16,
				"altAnim": false,
				"mustHitSection": true,
				"changeBPM": false,
				"bpm": 185
			},
			{
				"typeOfSection": 0,
				"sectionNotes": [],
				"sectionBeats": 4,
				"altAnim": false,
				"gfSection": false,
				"bpm": 185,
				"changeBPM": false,
				"mustHitSection": true
			},
			{
				"typeOfSection": 0,
				"sectionNotes": [],
				"sectionBeats": 4,
				"altAnim": false,
				"gfSection": false,
				"bpm": 185,
				"changeBPM": false,
				"mustHitSection": true
			},
			{
				"typeOfSection": 0,
				"sectionNotes": [],
				"sectionBeats": 4,
				"altAnim": false,
				"gfSection": false,
				"bpm": 185,
				"changeBPM": false,
				"mustHitSection": true
			},
			{
				"typeOfSection": 0,
				"sectionNotes": [],
				"sectionBeats": 4,
				"altAnim": false,
				"gfSection": false,
				"bpm": 110,
				"changeBPM": false,
				"mustHitSection": true
			},
			{
				"sectionBeats": 4,
				"sectionNotes": [],
				"typeOfSection": 0,
				"gfSection": false,
				"altAnim": false,
				"mustHitSection": true,
				"changeBPM": false,
				"bpm": 110
			},
			{
				"sectionBeats": 4,
				"sectionNotes": [],
				"typeOfSection": 0,
				"gfSection": false,
				"altAnim": false,
				"mustHitSection": true,
				"changeBPM": false,
				"bpm": 110
			},
			{
				"sectionBeats": 4,
				"sectionNotes": [],
				"typeOfSection": 0,
				"gfSection": false,
				"altAnim": false,
				"mustHitSection": true,
				"changeBPM": false,
				"bpm": 110
			},
			{
				"sectionBeats": 4,
				"sectionNotes": [],
				"typeOfSection": 0,
				"gfSection": false,
				"altAnim": false,
				"mustHitSection": true,
				"changeBPM": false,
				"bpm": 110
			},
			{
				"sectionBeats": 4,
				"sectionNotes": [],
				"typeOfSection": 0,
				"gfSection": false,
				"altAnim": false,
				"mustHitSection": true,
				"changeBPM": false,
				"bpm": 110
			},
			{
				"sectionBeats": 4,
				"sectionNotes": [],
				"typeOfSection": 0,
				"gfSection": false,
				"altAnim": false,
				"mustHitSection": true,
				"changeBPM": false,
				"bpm": 110
			},
			{
				"sectionBeats": 4,
				"sectionNotes": [],
				"typeOfSection": 0,
				"gfSection": false,
				"altAnim": false,
				"mustHitSection": true,
				"changeBPM": false,
				"bpm": 110
			},
			{
				"sectionBeats": 4,
				"sectionNotes": [],
				"typeOfSection": 0,
				"gfSection": false,
				"altAnim": false,
				"mustHitSection": true,
				"changeBPM": false,
				"bpm": 150
			},
			{
				"sectionBeats": 4,
				"sectionNotes": [],
				"typeOfSection": 0,
				"gfSection": false,
				"altAnim": false,
				"mustHitSection": true,
				"changeBPM": false,
				"bpm": 150
			},
			{
				"gfSection": false,
				"altAnim": false,
				"typeOfSection": 0,
				"sectionNotes": [],
				"bpm": 150,
				"sectionBeats": 4,
				"changeBPM": false,
				"mustHitSection": true
			},
			{
				"gfSection": false,
				"altAnim": false,
				"typeOfSection": 0,
				"sectionNotes": [],
				"bpm": 150,
				"sectionBeats": 4,
				"changeBPM": false,
				"mustHitSection": true
			},
			{
				"gfSection": false,
				"altAnim": false,
				"typeOfSection": 0,
				"sectionNotes": [],
				"bpm": 150,
				"sectionBeats": 4,
				"changeBPM": false,
				"mustHitSection": true
			},
			{
				"gfSection": false,
				"altAnim": false,
				"typeOfSection": 0,
				"sectionNotes": [],
				"bpm": 150,
				"sectionBeats": 4,
				"changeBPM": false,
				"mustHitSection": true
			},
			{
				"gfSection": false,
				"altAnim": false,
				"typeOfSection": 0,
				"sectionNotes": [],
				"bpm": 150,
				"sectionBeats": 4,
				"changeBPM": false,
				"mustHitSection": true
			}
		],
		"player2": "sfGODNEW",
		"player3": null,
		"song": "deathray",
		"stage": "yourgonnadie",
		"needsVoices": true,
		"validScore": true,
		"bpm": 150,
		"speed": 2.7
	}
}